davidkhala/google/adk/__init__.py
davidkhala/google/adk/built_in/__init__.py
davidkhala/google/adk/built_in/gcp.py
davidkhala_google_adk-0.0.0.dist-info/METADATA
davidkhala_google_adk-0.0.0.dist-info/WHEEL
davidkhala_google_adk-0.0.0.dist-info/RECORD
