Metadata-Version: 2.4
Name: davidkhala.google.adk
Version: 0.0.0
Requires-Python: >=3.12
Requires-Dist: google-adk
